[
{
"ID": 2307,
"T": "Episode 01 - The Arsenal",
"PLAY": "http://data002.coolsanime.in/siteuploads/files/sfd6/2993/Episode%2001%20-%20The%20Arsenal(CoolsAnime.Com).mp4",
"TP": "21:00",
"published@": "2018-02-26T09:39:57.028Z",
"updated@": "2018-04-10T15:08:06.032Z"
},
{
"ID": 2308,
"T": "Episode 02 - Thanos Rising",
"PLAY": "http://data002.coolsanime.in/siteuploads/files/sfd6/2995/Episode%2002%20-%20Thanos%20Rising(CoolsAnime.Com).mp4",
"TP": "21:00",
"published@": "2018-02-26T09:39:57.882Z",
"updated@": "2018-04-10T15:08:06.037Z"
},
{
"ID": 2309,
"T": "Episode 03 - Valhalla Can Wait",
"PLAY": "http://data002.coolsanime.in/siteuploads/files/sfd6/2997/Episode%2003%20-%20Valhalla%20Can%20Wait(CoolsAnime.Com).mp4",
"TP": "21:00",
"published@": "2018-02-26T09:39:58.894Z",
"updated@": "2018-04-10T15:08:07.150Z"
},
{
"ID": 2310,
"T": "Episode 04 - Ghosts of the Past",
"PLAY": "http://data002.coolsanime.in/siteuploads/files/sfd6/2999/Episode%2004%20-%20Ghosts%20of%20the%20Past(CoolsAnime.Com).mp4",
"TP": "21:00",
"published@": "2018-02-26T09:39:59.888Z",
"updated@": "2018-04-10T15:08:06.206Z"
},
{
"ID": 2311,
"T": "Episode 05 - Beneath the Surface",
"PLAY": "http://data002.coolsanime.in/siteuploads/files/sfd7/3001/Episode%2005%20-%20Beneath%20the%20Surface(CoolsAnime.Com).mp4",
"TP": "21:00",
"published@": "2018-02-26T09:40:00.777Z",
"updated@": "2018-04-10T15:08:06.046Z"
},
{
"ID": 2312,
"T": "Episode 06 - Nighthawk",
"PLAY": "http://data002.coolsanime.in/siteuploads/files/sfd7/3003/Episode%2006%20-%20Nighthawk(CoolsAnime.Com).mp4",
"TP": "21:00",
"published@": "2018-02-26T09:40:01.717Z",
"updated@": "2018-04-10T15:08:06.052Z"
},
{
"ID": 2313,
"T": "Episode 07 - The Age of Tony Stark",
"PLAY": "http://data002.coolsanime.in/siteuploads/files/sfd7/3007/Episode%2007%20-%20The%20Age%20of%20Tony%20Stark(CoolsAnime.Com).mp4",
"TP": "21:00",
"published@": "2018-02-26T09:40:02.817Z",
"updated@": "2018-04-10T15:08:07.205Z"
},
{
"ID": 2314,
"T": "Episode 08 - Head to Head",
"PLAY": "http://data002.coolsanime.in/siteuploads/files/sfd7/3009/Episode%2008%20-%20Head%20to%20Head(CoolsAnime.Com).mp4",
"TP": "21:00",
"published@": "2018-02-26T09:40:03.819Z",
"updated@": "2018-04-10T15:08:06.057Z"
},
{
"ID": 2315,
"T": "Episode 09 - The Dark Avengers",
"PLAY": "http://data002.coolsanime.in/siteuploads/files/sfd7/3011/Episode%2009%20-%20The%20Dark%20Avengers(CoolsAnime.Com).mp4",
"TP": "21:00",
"published@": "2018-02-26T09:40:04.819Z",
"updated@": "2018-04-10T15:08:06.061Z"
},
{
"ID": 2316,
"T": "Episode 10 - Back to the Learning Hall",
"PLAY": "http://data002.coolsanime.in/siteuploads/files/sfd7/3013/Episode%2010%20-%20Back%20to%20the%20Learning%20Hall(CoolsAnime.Com).mp4",
"TP": "21:00",
"published@": "2018-02-26T09:40:05.742Z",
"updated@": "2018-04-10T15:08:06.066Z"
},
{
"ID": 2317,
"T": "Episode 11 - Downgraded",
"PLAY": "http://data002.coolsanime.in/siteuploads/files/sfd7/3015/Episode%2011%20-%20Downgraded(CoolsAnime.Com).mp4",
"TP": "21:00",
"published@": "2018-02-26T09:40:06.703Z",
"updated@": "2018-04-10T15:08:06.071Z"
},
{
"ID": 2318,
"T": "Episode 12 - Widows Run",
"PLAY": "http://data002.coolsanime.in/siteuploads/files/sfd7/3017/Episode%2012%20-%20Widows%20Run(CoolsAnime.Com).mp4",
"TP": "21:00",
"published@": "2018-02-26T09:40:07.597Z",
"updated@": "2018-04-10T15:08:06.075Z"
},
{
"ID": 2319,
"T": "Episode 13 - Thanos Triumphant",
"PLAY": "http://data002.coolsanime.in/siteuploads/files/sfd7/3019/Episode%2013%20-%20Thanos%20Triumphant(CoolsAnime.Com).mp4",
"TP": "21:00",
"published@": "2018-02-26T09:40:08.527Z",
"updated@": "2018-04-10T15:08:06.080Z"
},
{
"ID": 2320,
"T": "Episode 14 - Crack in the System",
"PLAY": "http://data002.coolsanime.in/siteuploads/files/sfd7/3021/Episode%2014%20-%20Crack%20in%20the%20System(CoolsAnime.Com).mp4",
"TP": "21:00",
"published@": "2018-02-26T09:40:09.522Z",
"updated@": "2018-04-10T15:08:06.086Z"
},
{
"ID": 2321,
"T": "Episode 15 - Avengers Disassembled",
"PLAY": "http://data002.coolsanime.in/siteuploads/files/sfd7/3023/Episode%2015%20-%20Avengers%20Disassembled(CoolsAnime.Com).mp4",
"TP": "21:00",
"published@": "2018-02-26T09:40:10.451Z",
"updated@": "2018-04-10T15:08:06.092Z"
},
{
"ID": 2322,
"T": "Episode 16 - Small Time Heroes",
"PLAY": "http://data002.coolsanime.in/siteuploads/files/sfd7/3025/Episode%2016%20-%20Small%20Time%20Heroes(CoolsAnime.Com).mp4",
"TP": "21:00",
"published@": "2018-02-26T09:40:11.377Z",
"updated@": "2018-04-10T15:08:06.096Z"
},
{
"ID": 2323,
"T": "Episode 17 - Secret Avengers",
"PLAY": "http://data002.coolsanime.in/siteuploads/files/sfd7/3027/Episode%2017%20-%20Secret%20Avengers(CoolsAnime.Com).mp4",
"TP": "21:00",
"published@": "2018-02-26T09:40:12.405Z",
"updated@": "2018-04-10T15:08:06.101Z"
},
{
"ID": 2324,
"T": "Episode 18 - The Ultron Outbreak",
"PLAY": "http://data002.coolsanime.in/siteuploads/files/sfd7/3030/Episode%2018%20-%20The%20Ultron%20Outbreak(CoolsAnime.Com).mp4",
"TP": "21:00",
"published@": "2018-02-26T09:40:13.430Z",
"updated@": "2018-04-10T15:08:06.105Z"
},
{
"ID": 2325,
"T": "Episode 19 - The New Guy",
"PLAY": "http://data002.coolsanime.in/siteuploads/files/sfd7/3032/Episode%2019%20-%20The%20New%20Guy(CoolsAnime.Com).mp4",
"TP": "21:00",
"published@": "2018-02-26T09:40:14.479Z",
"updated@": "2018-04-10T15:08:06.109Z"
},
{
"ID": 2326,
"T": "Episode 20 - Terminal Velocity",
"PLAY": "http://data002.coolsanime.in/siteuploads/files/sfd7/3034/Episode%2020%20-%20Terminal%20Velocity(CoolsAnime.Com).mp4",
"TP": "21:00",
"published@": "2018-02-26T09:40:15.588Z",
"updated@": "2018-04-10T15:08:06.114Z"
},
{
"ID": 2327,
"T": "Episode 21 - Spectrums",
"PLAY": "http://data002.coolsanime.in/siteuploads/files/sfd7/3036/Episode%2021%20-%20Spectrums(CoolsAnime.Com).mp4",
"TP": "21:00",
"published@": "2018-02-26T09:40:16.792Z",
"updated@": "2018-04-10T15:08:06.118Z"
},
{
"ID": 2328,
"T": "Episode 22 - Midgard Crisis",
"PLAY": "http://data002.coolsanime.in/siteuploads/files/sfd7/3038/Episode%2022%20-%20Midgard%20Crisis(CoolsAnime.Com).mp4",
"TP": "21:00",
"published@": "2018-02-26T09:40:18.074Z",
"updated@": "2018-04-10T15:08:07.210Z"
},
{
"ID": 2329,
"T": "Episode 23 - Avengers Last Stand",
"PLAY": "http://data002.coolsanime.in/siteuploads/files/sfd7/3041/Episode%2023%20-%20Avengers%20Last%20Stand(CoolsAnime.Com).mp4",
"published@": "2018-02-26T09:40:19.168Z",
"updated@": "2018-04-10T15:08:06.123Z"
},
{
"ID": 2330,
"T": "Episode 24 - Avengers Underground",
"PLAY": "http://data002.coolsanime.in/siteuploads/files/sfd7/3043/Episode%2024%20-%20Avengers%20Underground(CoolsAnime.Com).mp4",
"TP": "21:00",
"published@": "2018-02-26T09:40:20.425Z",
"updated@": "2018-04-10T15:08:06.126Z"
},
{
"ID": 2331,
"T": "Episode 25 - New Frontier",
"PLAY": "http://data002.coolsanime.in/siteuploads/files/sfd7/3045/Episode%2025%20-%20New%20Frontier(CoolsAnime.Com).mp4",
"TP": "21:00",
"published@": "2018-02-26T09:40:21.764Z",
"updated@": "2018-04-10T15:08:06.131Z"
},
{
"ID": 2332,
"T": "Episode 26 - Avengers World Season 02 Finale",
"PLAY": "http://data002.coolsanime.in/siteuploads/files/sfd7/3047/Episode%2026%20-%20Avengers%20World%20Season%2002%20Finale(CoolsAnime.Com).mp4",
"TP": "21:00",
"published@": "2018-02-26T09:40:23.084Z",
"updated@": "2018-04-10T15:08:06.135Z"
}
]